LICENSE.md
MANIFEST.in
README.md
example.png
requirements.txt
setup.cfg
setup.py
dj_field_filemanager/__init__.py
dj_field_filemanager/admin.py
dj_field_filemanager/api.py
dj_field_filemanager/apps.py
dj_field_filemanager/models.py
dj_field_filemanager/permissions.py
dj_field_filemanager/serializers.py
dj_field_filemanager/settings.py
dj_field_filemanager/signals.py
dj_field_filemanager/storage.py
dj_field_filemanager/urls.py
dj_field_filemanager/widgets.py
dj_field_filemanager.egg-info/PKG-INFO
dj_field_filemanager.egg-info/SOURCES.txt
dj_field_filemanager.egg-info/dependency_links.txt
dj_field_filemanager.egg-info/not-zip-safe
dj_field_filemanager.egg-info/requires.txt
dj_field_filemanager.egg-info/top_level.txt
dj_field_filemanager/management/__init__.py
dj_field_filemanager/management/commands/__init__.py
dj_field_filemanager/management/commands/generate_thumbnails.py
dj_field_filemanager/static/.DS_Store
dj_field_filemanager/static/field-filemanager/field-filemanager-0.2.8-init.js
dj_field_filemanager/static/field-filemanager/field-filemanager-0.2.8.css
dj_field_filemanager/static/field-filemanager/vue-2.6.10.min.js
dj_field_filemanager/static/field-filemanager/field-filemanager-0.2.7/demo.html
dj_field_filemanager/static/field-filemanager/field-filemanager-0.2.7/filemanager.common.js
dj_field_filemanager/static/field-filemanager/field-filemanager-0.2.7/filemanager.common.js.map
dj_field_filemanager/static/field-filemanager/field-filemanager-0.2.7/filemanager.umd.js
dj_field_filemanager/static/field-filemanager/field-filemanager-0.2.7/filemanager.umd.js.map
dj_field_filemanager/static/field-filemanager/field-filemanager-0.2.8/filemanager.css
dj_field_filemanager/static/field-filemanager/field-filemanager-0.2.8/filemanager.umd.min.js
dj_field_filemanager/static/field-filemanager/field-filemanager-0.2.8/filemanager.umd.min.js.map
dj_field_filemanager/templates/dj_field_filemanager/field_filemanager_widget.html
dj_field_filemanager/templates/dj_field_filemanager/upload_to_folder.html
dj_field_filemanager/templatetags/__init__.py
dj_field_filemanager/templatetags/dj_field_filemanager.py
dj_field_filemanager/viewsets/__init__.py
dj_field_filemanager/viewsets/model.py
dj_field_filemanager/viewsets/storage.py