Metadata-Version: 1.1
Name: dj-field-filemanager
Version: 0.2.9
Summary: Django: Add file manager to a model
Home-page: https://github.com/Microdisseny/django-field-filemanager
Author: MICRODISSENY GISCUBE SL
Author-email: tech@microdisseny.com
License: MIT License
Platform: OS Independent
Classifier: Framework :: Django
Classifier: Intended Audience :: Developers
Classifier: License :: OSI Approved :: MIT License
Classifier: Operating System :: OS Independent
Classifier: Topic :: Software Development
Classifier: Programming Language :: Python :: 3
Classifier: Environment :: Web Environment
Classifier: Development Status :: 4 - Beta
Classifier: Topic :: Software Development :: Libraries :: Python Modules
